urielplus/__init__.py
urielplus/base_uriel.py
urielplus/urielplus.py
urielplus/urielplus_databases.py
urielplus/urielplus_imputation.py
urielplus/urielplus_querying.py
urielplus/database/__init__.py
urielplus/database/original_uriel/__init__.py
urielplus/database/original_uriel/family_features.npz
urielplus/database/original_uriel/features.npz
urielplus/database/original_uriel/geocoord_features.npz
urielplus/database/original_uriel/script_features.npz
urielplus/database/urielplus_csvs/__init__.py
urielplus/database/urielplus_csvs/apics_data.csv
urielplus/database/urielplus_csvs/bdproto_data.csv
urielplus/database/urielplus_csvs/dialects.csv
urielplus/database/urielplus_csvs/english_dialect_data.csv
urielplus/database/urielplus_csvs/grambank_data.csv
urielplus/database/urielplus_csvs/lang_fam_geo.csv
urielplus/database/urielplus_csvs/saphon_data.csv
urielplus/database/urielplus_csvs/script_data.csv
urielplus/database/urielplus_csvs/uriel_glottocode_map.csv
urielplus-1.2.dist-info/licenses/LICENSE.txt
urielplus-1.2.dist-info/METADATA
urielplus-1.2.dist-info/WHEEL
urielplus-1.2.dist-info/top_level.txt
urielplus-1.2.dist-info/RECORD
