Metadata-Version: 2.4
Name: urielplus
Version: 1.2
Summary: URIEL+: Knowledge base for natural language processing
Home-page: https://github.com/Masonshipton25/URIELPlus
Author: Mason Shipton
Author-email: masonshipton25@gmail.com
License: Apache 2.0 License
Project-URL: Bug Tracker, https://github.com/Masonshipton25/URIELPlus/issues
Classifier: Programming Language :: Python :: 3
Classifier: License :: OSI Approved :: Apache Software License
Classifier: Operating System :: OS Independent
Requires-Python: >=3.10
License-File: LICENSE.txt
Requires-Dist: numpy>=1.26.1
Requires-Dist: tensorflow>=2.11.1
Requires-Dist: tensorflow-addons>=0.19
Requires-Dist: scikit-learn>=1.5.1
Requires-Dist: scipy>=1.14.1
Requires-Dist: pandas>=2.2.2
Requires-Dist: contexttimer>=0.3.3
Requires-Dist: fancyimpute>=0.7.0
Requires-Dist: joblib>=1.4.2
Requires-Dist: setuptools>=68.2.0
Provides-Extra: midaspy
Requires-Dist: MIDASpy>=1.4.0; extra == "midaspy"
Requires-Dist: tensorflow<2.12.0; extra == "midaspy"
Requires-Dist: tensorflow-addons<0.20; extra == "midaspy"
Dynamic: author
Dynamic: author-email
Dynamic: classifier
Dynamic: description
Dynamic: description-content-type
Dynamic: home-page
Dynamic: license
Dynamic: license-file
Dynamic: project-url
Dynamic: provides-extra
Dynamic: requires-dist
Dynamic: requires-python
Dynamic: summary
